LICENSE
MANIFEST.in
README.md
pyproject.toml
setup.py
gwsurrogate/__init__.py
gwsurrogate/catalog.py
gwsurrogate/parametric_funcs.py
gwsurrogate/pycbc.py
gwsurrogate/surrogate.py
gwsurrogate/surrogateIO.py
gwsurrogate.egg-info/PKG-INFO
gwsurrogate.egg-info/SOURCES.txt
gwsurrogate.egg-info/dependency_links.txt
gwsurrogate.egg-info/entry_points.txt
gwsurrogate.egg-info/requires.txt
gwsurrogate.egg-info/top_level.txt
gwsurrogate/eval_pysur/__init__.py
gwsurrogate/eval_pysur/evaluate_fit.py
gwsurrogate/new/__init__.py
gwsurrogate/new/nodeFunction.py
gwsurrogate/new/precessing_surrogate.py
gwsurrogate/new/saveH5Object.py
gwsurrogate/new/spline_coef_evaluation.py
gwsurrogate/new/spline_evaluation.py
gwsurrogate/new/surrogate.py
gwsurrogate/new/test_nodeFunction.py
gwsurrogate/new/test_saveH5Object.py
gwsurrogate/new/test_surrogate.py
gwsurrogate/new/tidal_functions.py
gwsurrogate/precessing_utils/Readme.md
gwsurrogate/precessing_utils/__init__.py
gwsurrogate/precessing_utils/setup.py
gwsurrogate/precessing_utils/include/precessing_utils.h
gwsurrogate/precessing_utils/src/precessing_utils.c
gwsurrogate/spline_interp_Cwrapper/Readme.md
gwsurrogate/spline_interp_Cwrapper/__init__.py
gwsurrogate/spline_interp_Cwrapper/_spline_interp.c
gwsurrogate/spline_interp_Cwrapper/setup.py
gwsurrogate/spline_interp_Cwrapper/spline_interp_Cwrapper.py
test/add_model_regression_data.py
test/check_model_regression_data.py
test/conftest.py
test/download_regression_models.py
test/test_model_regression.py
test/test_regression.py
test/test_unit.py
tutorial/TutorialSurrogate/EOB_q1_2_NoSpin_Mode22/l2_m2_len12239M_SurID19poly/B_1.txt
tutorial/TutorialSurrogate/EOB_q1_2_NoSpin_Mode22/l2_m2_len12239M_SurID19poly/B_2.txt
tutorial/TutorialSurrogate/EOB_q1_2_NoSpin_Mode22/l2_m2_len12239M_SurID19poly/R_1.txt
tutorial/TutorialSurrogate/EOB_q1_2_NoSpin_Mode22/l2_m2_len12239M_SurID19poly/R_2.txt
tutorial/TutorialSurrogate/EOB_q1_2_NoSpin_Mode22/l2_m2_len12239M_SurID19poly/V_1.txt
tutorial/TutorialSurrogate/EOB_q1_2_NoSpin_Mode22/l2_m2_len12239M_SurID19poly/V_2.txt
tutorial/TutorialSurrogate/EOB_q1_2_NoSpin_Mode22/l2_m2_len12239M_SurID19poly/affine_map.txt
