Metadata-Version: 2.1
Name: gwsurrogate
Version: 1.1.8
Summary: An easy to use interface to gravitational wave surrogate models
Author: Jonathan Blackman, Scott Field, Chad Galley, Vijay Varma, Kevin Barkett
Author-email: sfield@umassd.edu
License: MIT
Classifier: Intended Audience :: Other Audience
Classifier: Intended Audience :: Science/Research
Classifier: Natural Language :: English
Classifier: License :: OSI Approved :: MIT License
Classifier: Programming Language :: Python
Classifier: Topic :: Scientific/Engineering
Classifier: Topic :: Scientific/Engineering :: Mathematics
Classifier: Topic :: Scientific/Engineering :: Physics
License-File: LICENSE
Requires-Dist: numpy>=1.7
Requires-Dist: requests
Requires-Dist: scipy
Requires-Dist: h5py
Requires-Dist: pytest
Requires-Dist: scikit-learn
Requires-Dist: gwtools
Requires-Dist: matplotlib
